{
  "project_info": {
    "project_number": "456016473426",
    "firebase_url": "https://pet-share.firebaseio.com",
    "project_id": "pet-share",
    "storage_bucket": "pet-share.appspot.com"
  },
  "client": [
    {
      "client_info": {
        "mobilesdk_app_id": "1:456016473426:android:987b9b2dc7b86e7f",
        "android_client_info": {
          "package_name": "wpi.hphong.petshare"
        }
      },
      "oauth_client": [
        {
          "client_id": "456016473426-iapou0fl5tp3ck0mrjac43k8gorlctl4.apps.googleusercontent.com",
          "client_type": 3
        }
      ],
      "api_key": [
        {
          "current_key": "AIzaSyABBGhbS_7sHyqvUCQ_hsoeM12umnWIjLc"
        }
      ],
      "services": {
        "analytics_service": {
          "status": 1
        },
        "appinvite_service": {
          "status": 1,
          "other_platform_oauth_client": []
        },
        "ads_service": {
          "status": 2
        }
      }
    }
  ],
  "configuration_version": "1"
}